taskshed/__init__.py
taskshed/datastores/__init__.py
taskshed/datastores/base_datastore.py
taskshed/datastores/memory_datastore.py
taskshed/datastores/mysql_datastore.py
taskshed/datastores/redis_datastore.py
taskshed/models/__init__.py
taskshed/models/task_models.py
taskshed/schedulers/__init__.py
taskshed/schedulers/async_scheduler.py
taskshed/utils/errors.py
taskshed/workers/__init__.py
taskshed/workers/base_worker.py
taskshed/workers/event_driven_worker.py
taskshed/workers/polling_worker.py
taskshed-0.7.0.dist-info/licenses/LICENSE
taskshed-0.7.0.dist-info/METADATA
taskshed-0.7.0.dist-info/WHEEL
taskshed-0.7.0.dist-info/top_level.txt
taskshed-0.7.0.dist-info/RECORD
