Metadata-Version: 2.4
Name: taskshed
Version: 0.7.0
Summary: A high-performance, asynchronous, ready for production task scheduling framework written in Python.
Author-email: Jacob Strauss <jacob@meetchase.ai>
License: MIT
Project-URL: Homepage, https://github.com/Chase-Labs/taskshed
Project-URL: Documentation, https://chase-labs.github.io/taskshed/
Project-URL: Bug Tracker, https://github.com/Chase-Labs/taskshed/issues
Keywords: task scheduling,job scheduling,scheduler,cron,background jobs,background tasks,periodic tasks,recurring tasks,asyncio,asynchronous,distributed,worker,queue,redis,mysql
Classifier: Development Status :: 5 - Production/Stable
Classifier: Intended Audience :: Developers
Classifier: License :: OSI Approved :: MIT License
Classifier: Operating System :: OS Independent
Classifier: Topic :: Software Development :: Libraries :: Python Modules
Classifier: Programming Language :: Python
Classifier: Programming Language :: Python :: 3.8
Classifier: Programming Language :: Python :: 3.9
Classifier: Programming Language :: Python :: 3.10
Classifier: Programming Language :: Python :: 3.11
Classifier: Programming Language :: Python :: 3.12
Classifier: Programming Language :: Python :: 3.13
Requires-Python: >=3.8
License-File: LICENSE
Provides-Extra: mysql
Requires-Dist: aiomysql>=0.2.0; extra == "mysql"
Provides-Extra: redis
Requires-Dist: redis>=6.0.0; extra == "redis"
Provides-Extra: all
Requires-Dist: taskshed[mysql,redis]; extra == "all"
Dynamic: license-file
